sentinel_ai/__init__.py
sentinel_ai/core.py
sentinel_ai/policy.py
sentinel_ai/redactor.py
sentinel_ai/config/policy.yaml
sentinel_ai/examples/integration_examples.py
sentinel_ai_guard-1.0.0.dist-info/licenses/LICENSE
sentinel_ai_guard-1.0.0.dist-info/METADATA
sentinel_ai_guard-1.0.0.dist-info/WHEEL
sentinel_ai_guard-1.0.0.dist-info/top_level.txt
sentinel_ai_guard-1.0.0.dist-info/RECORD
