Metadata-Version: 2.4
Name: sentinel-ai-guard
Version: 1.0.0
Summary: Lightweight middleware to prevent semantic hijacking in AI agents
Author: Sentinel-AI Contributors
License: MIT
Project-URL: Homepage, https://github.com/yourusername/sentinel-ai
Project-URL: Documentation, https://github.com/yourusername/sentinel-ai#readme
Project-URL: Repository, https://github.com/yourusername/sentinel-ai
Project-URL: Issues, https://github.com/yourusername/sentinel-ai/issues
Keywords: ai,security,llm,agents,prompt-injection,semantic-hijacking
Classifier: Development Status :: 4 - Beta
Classifier: Intended Audience :: Developers
Classifier: License :: OSI Approved :: MIT License
Classifier: Programming Language :: Python :: 3
Classifier: Programming Language :: Python :: 3.8
Classifier: Programming Language :: Python :: 3.9
Classifier: Programming Language :: Python :: 3.10
Classifier: Programming Language :: Python :: 3.11
Classifier: Programming Language :: Python :: 3.12
Classifier: Topic :: Software Development :: Libraries :: Python Modules
Classifier: Topic :: Security
Classifier: Topic :: Scientific/Engineering :: Artificial Intelligence
Requires-Python: >=3.8
License-File: LICENSE
Requires-Dist: pyyaml>=6.0
Provides-Extra: dev
Requires-Dist: pytest>=7.0; extra == "dev"
Requires-Dist: pytest-cov>=4.0; extra == "dev"
Requires-Dist: black>=23.0; extra == "dev"
Requires-Dist: flake8>=6.0; extra == "dev"
Requires-Dist: mypy>=1.0; extra == "dev"
Provides-Extra: examples
Requires-Dist: openai>=1.0; extra == "examples"
Requires-Dist: anthropic>=0.18; extra == "examples"
Dynamic: license-file
